<?xml version="1.0" encoding="utf-8"?>
<clothing-items>
 <clothing>
  <id>
   330701432
  </id>
  <name>
   Brooks Hat H-1227
  </name>
  <category>
   Hat
  </category>
  <size>
   S
  </size>
  <color>
   Голубой
  </color>
  <material>
   Нейлон
  </material>
  <price>
   321954
  </price>
  <rating>
   1.3
  </rating>
  <reviews>
   80801
  </reviews>
 </clothing>
 <clothing>
  <id>
   650790263
  </id>
  <name>
   PleinSport Shirt E-6983
  </name>
  <category>
   Shirt
  </category>
  <size>
   XXL
  </size>
  <color>
   Желтый
  </color>
  <material>
   Кожа
  </material>
  <price>
   272937
  </price>
  <rating>
   1.85
  </rating>
  <reviews>
   289538
  </reviews>
  <new>
   -
  </new>
  <exclusive>
   no
  </exclusive>
  <sporty>
   yes
  </sporty>
 </clothing>
 <clothing>
  <id>
   368615108
  </id>
  <name>
   Converse Belts S-3349
  </name>
  <category>
   Belts
  </category>
  <size>
   S
  </size>
  <color>
   Зеленый
  </color>
  <material>
   Хлопок
  </material>
  <price>
   172245
  </price>
  <rating>
   4.96
  </rating>
  <reviews>
   123173
  </reviews>
  <sporty>
   no
  </sporty>
 </clothing>
 <clothing>
  <id>
   921813677
  </id>
  <name>
   Addidas Sweater A-1463
  </name>
  <category>
   Sweater
  </category>
  <size>
   S
  </size>
  <color>
   Оранжевый
  </color>
  <material>
   Нейлон
  </material>
  <price>
   964068
  </price>
  <rating>
   4.35
  </rating>
  <reviews>
   468397
  </reviews>
  <sporty>
   yes
  </sporty>
 </clothing>
 <clothing>
  <id>
   815079043
  </id>
  <name>
   Reebok Pants E-7376
  </name>
  <category>
   Pants
  </category>
  <size>
   XL
  </size>
  <color>
   Оранжевый
  </color>
  <material>
   Хлопок
  </material>
  <price>
   633609
  </price>
  <rating>
   1.11
  </rating>
  <reviews>
   340283
  </reviews>
  <new>
   -
  </new>
  <exclusive>
   no
  </exclusive>
  <sporty>
   no
  </sporty>
 </clothing>
 <clothing>
  <id>
   245958723
  </id>
  <name>
   DC T-shirt Q-7313
  </name>
  <category>
   T-shirt
  </category>
  <size>
   XL
  </size>
  <color>
   Красный
  </color>
  <material>
   Лен
  </material>
  <price>
   434863
  </price>
  <rating>
   1.13
  </rating>
  <reviews>
   277357
  </reviews>
  <exclusive>
   no
  </exclusive>
  <sporty>
   no
  </sporty>
 </clothing>
 <clothing>
  <id>
   930790238
  </id>
  <name>
   PleinSport Pants P-5211
  </name>
  <category>
   Pants
  </category>
  <size>
   XXL
  </size>
  <color>
   Красный
  </color>
  <material>
   Лен
  </material>
  <price>
   208497
  </price>
  <rating>
   2.76
  </rating>
  <reviews>
   276230
  </reviews>
  <new>
   -
  </new>
  <exclusive>
   no
  </exclusive>
 </clothing>
 <clothing>
  <id>
   769811822
  </id>
  <name>
   Puma Gloves M-3355
  </name>
  <category>
   Gloves
  </category>
  <size>
   XL
  </size>
  <color>
   Желтый
  </color>
  <material>
   Хлопок
  </material>
  <price>
   719961
  </price>
  <rating>
   1.79
  </rating>
  <reviews>
   750737
  </reviews>
  <exclusive>
   no
  </exclusive>
  <sporty>
   no
  </sporty>
 </clothing>
 <clothing>
  <id>
   582829470
  </id>
  <name>
   Lacoste Hat P-3025
  </name>
  <category>
   Hat
  </category>
  <size>
   L
  </size>
  <color>
   Зеленый
  </color>
  <material>
   Хлопок
  </material>
  <price>
   240734
  </price>
  <rating>
   4.25
  </rating>
  <reviews>
   988873
  </reviews>
  <exclusive>
   yes
  </exclusive>
  <sporty>
   no
  </sporty>
 </clothing>
 <clothing>
  <id>
   801568464
  </id>
  <name>
   Lacoste Handbags L-6599
  </name>
  <category>
   Handbags
  </category>
  <size>
   XXL
  </size>
  <color>
   Зеленый
  </color>
  <material>
   Кожа
  </material>
  <price>
   735392
  </price>
  <rating>
   1.05
  </rating>
  <reviews>
   42113
  </reviews>
  <new>
   +
  </new>
  <exclusive>
   no
  </exclusive>
  <sporty>
   yes
  </sporty>
 </clothing>
 <clothing>
  <id>
   459873621
  </id>
  <name>
   PleinSport Socks G-8954
  </name>
  <category>
   Socks
  </category>
  <size>
   M
  </size>
  <color>
   Оранжевый
  </color>
  <material>
   Шерсть
  </material>
  <price>
   660807
  </price>
  <rating>
   3.57
  </rating>
  <reviews>
   454830
  </reviews>
  <new>
   -
  </new>
  <exclusive>
   yes
  </exclusive>
 </clothing>
 <clothing>
  <id>
   996613607
  </id>
  <name>
   Puma Skirt P-2948
  </name>
  <category>
   Skirt
  </category>
  <size>
   M
  </size>
  <color>
   Оранжевый
  </color>
  <material>
   Шелк
  </material>
  <price>
   304759
  </price>
  <rating>
   1.23
  </rating>
  <reviews>
   467003
  </reviews>
  <new>
   +
  </new>
  <exclusive>
   no
  </exclusive>
 </clothing>
 <clothing>
  <id>
   443554105
  </id>
  <name>
   Vans Handbags C-9516
  </name>
  <category>
   Handbags
  </category>
  <size>
   XXL
  </size>
  <color>
   Фиолетовый
  </color>
  <material>
   Полиэстер
  </material>
  <price>
   468148
  </price>
  <rating>
   2.47
  </rating>
  <reviews>
   352688
  </reviews>
  <new>
   -
  </new>
  <exclusive>
   yes
  </exclusive>
 </clothing>
 <clothing>
  <id>
   829596966
  </id>
  <name>
   Ellesse T-shirt B-8109
  </name>
  <category>
   T-shirt
  </category>
  <size>
   M
  </size>
  <color>
   Красный
  </color>
  <material>
   Нейлон
  </material>
  <price>
   431928
  </price>
  <rating>
   3.26
  </rating>
  <reviews>
   487751
  </reviews>
  <new>
   -
  </new>
  <sporty>
   yes
  </sporty>
 </clothing>
 <clothing>
  <id>
   765820620
  </id>
  <name>
   Vans Jeans F-9639
  </name>
  <category>
   Jeans
  </category>
  <size>
   S
  </size>
  <color>
   Оранжевый
  </color>
  <material>
   Шерсть
  </material>
  <price>
   513157
  </price>
  <rating>
   3.33
  </rating>
  <reviews>
   922130
  </reviews>
  <new>
   -
  </new>
  <sporty>
   no
  </sporty>
 </clothing>
 <clothing>
  <id>
   192944596
  </id>
  <name>
   PleinSport Sweater L-6252
  </name>
  <category>
   Sweater
  </category>
  <size>
   L
  </size>
  <color>
   Синий
  </color>
  <material>
   Полиэстер
  </material>
  <price>
   454420
  </price>
  <rating>
   3.15
  </rating>
  <reviews>
   544980
  </reviews>
  <sporty>
   no
  </sporty>
 </clothing>
 <clothing>
  <id>
   731928711
  </id>
  <name>
   Puma Handbags R-3419
  </name>
  <category>
   Handbags
  </category>
  <size>
   XXL
  </size>
  <color>
   Красный
  </color>
  <material>
   Нейлон
  </material>
  <price>
   813658
  </price>
  <rating>
   1.05
  </rating>
  <reviews>
   861703
  </reviews>
  <new>
   -
  </new>
  <exclusive>
   yes
  </exclusive>
 </clothing>
 <clothing>
  <id>
   387497197
  </id>
  <name>
   Puma Skirt K-3776
  </name>
  <category>
   Skirt
  </category>
  <size>
   L
  </size>
  <color>
   Оранжевый
  </color>
  <material>
   Полиэстер
  </material>
  <price>
   652410
  </price>
  <rating>
   4.05
  </rating>
  <reviews>
   831188
  </reviews>
  <sporty>
   no
  </sporty>
 </clothing>
 <clothing>
  <id>
   352039429
  </id>
  <name>
   Fila Jeans I-8446
  </name>
  <category>
   Jeans
  </category>
  <size>
   XL
  </size>
  <color>
   Фиолетовый
  </color>
  <material>
   Нейлон
  </material>
  <price>
   116661
  </price>
  <rating>
   3.32
  </rating>
  <reviews>
   945857
  </reviews>
  <new>
   -
  </new>
  <exclusive>
   yes
  </exclusive>
 </clothing>
 <clothing>
  <id>
   590233508
  </id>
  <name>
   Asics Handbags F-9387
  </name>
  <category>
   Handbags
  </category>
  <size>
   XXL
  </size>
  <color>
   Фиолетовый
  </color>
  <material>
   Нейлон
  </material>
  <price>
   160095
  </price>
  <rating>
   2.29
  </rating>
  <reviews>
   960410
  </reviews>
  <new>
   -
  </new>
  <exclusive>
   no
  </exclusive>
 </clothing>
</clothing-items>
