<?xml version="1.0" encoding="utf-8"?>
<clothing-items>
 <clothing>
  <id>
   723206928
  </id>
  <name>
   Nike T-shirt V-1192
  </name>
  <category>
   T-shirt
  </category>
  <size>
   M
  </size>
  <color>
   Желтый
  </color>
  <material>
   Шерсть
  </material>
  <price>
   917344
  </price>
  <rating>
   3.69
  </rating>
  <reviews>
   217296
  </reviews>
  <sporty>
   no
  </sporty>
 </clothing>
 <clothing>
  <id>
   802083632
  </id>
  <name>
   Under Armour Gloves Z-3933
  </name>
  <category>
   Gloves
  </category>
  <size>
   M
  </size>
  <color>
   Синий
  </color>
  <material>
   Шерсть
  </material>
  <price>
   927077
  </price>
  <rating>
   1.97
  </rating>
  <reviews>
   663356
  </reviews>
  <new>
   +
  </new>
  <exclusive>
   yes
  </exclusive>
  <sporty>
   yes
  </sporty>
 </clothing>
 <clothing>
  <id>
   233853840
  </id>
  <name>
   Reebok Umbrellas U-9458
  </name>
  <category>
   Umbrellas
  </category>
  <size>
   XXL
  </size>
  <color>
   Оранжевый
  </color>
  <material>
   Полиэстер
  </material>
  <price>
   514694
  </price>
  <rating>
   2.85
  </rating>
  <reviews>
   53148
  </reviews>
 </clothing>
 <clothing>
  <id>
   169641353
  </id>
  <name>
   Vans Handbags V-9205
  </name>
  <category>
   Handbags
  </category>
  <size>
   L
  </size>
  <color>
   Фиолетовый
  </color>
  <material>
   Полиэстер
  </material>
  <price>
   244499
  </price>
  <rating>
   2.51
  </rating>
  <reviews>
   698827
  </reviews>
  <new>
   -
  </new>
  <sporty>
   no
  </sporty>
 </clothing>
 <clothing>
  <id>
   774094586
  </id>
  <name>
   Ellesse T-shirt B-1049
  </name>
  <category>
   T-shirt
  </category>
  <size>
   S
  </size>
  <color>
   Голубой
  </color>
  <material>
   Нейлон
  </material>
  <price>
   424456
  </price>
  <rating>
   2.81
  </rating>
  <reviews>
   703989
  </reviews>
  <new>
   -
  </new>
  <exclusive>
   no
  </exclusive>
  <sporty>
   no
  </sporty>
 </clothing>
 <clothing>
  <id>
   737325441
  </id>
  <name>
   Puma Jeans I-2626
  </name>
  <category>
   Jeans
  </category>
  <size>
   L
  </size>
  <color>
   Желтый
  </color>
  <material>
   Вискоза
  </material>
  <price>
   380301
  </price>
  <rating>
   4.64
  </rating>
  <reviews>
   10330
  </reviews>
  <new>
   -
  </new>
  <exclusive>
   yes
  </exclusive>
 </clothing>
 <clothing>
  <id>
   788442291
  </id>
  <name>
   Asics Jacket O-7775
  </name>
  <category>
   Jacket
  </category>
  <size>
   S
  </size>
  <color>
   Фиолетовый
  </color>
  <material>
   Шерсть
  </material>
  <price>
   963747
  </price>
  <rating>
   4.43
  </rating>
  <reviews>
   183658
  </reviews>
  <new>
   -
  </new>
 </clothing>
 <clothing>
  <id>
   214832714
  </id>
  <name>
   Puma Handbags O-9392
  </name>
  <category>
   Handbags
  </category>
  <size>
   XXL
  </size>
  <color>
   Красный
  </color>
  <material>
   Лен
  </material>
  <price>
   564702
  </price>
  <rating>
   4.95
  </rating>
  <reviews>
   3628
  </reviews>
  <new>
   -
  </new>
  <exclusive>
   yes
  </exclusive>
  <sporty>
   no
  </sporty>
 </clothing>
 <clothing>
  <id>
   817097783
  </id>
  <name>
   Reebok Handbags U-7557
  </name>
  <category>
   Handbags
  </category>
  <size>
   S
  </size>
  <color>
   Голубой
  </color>
  <material>
   Шерсть
  </material>
  <price>
   847727
  </price>
  <rating>
   4.36
  </rating>
  <reviews>
   120602
  </reviews>
 </clothing>
 <clothing>
  <id>
   813610403
  </id>
  <name>
   Puma Handbags J-7442
  </name>
  <category>
   Handbags
  </category>
  <size>
   L
  </size>
  <color>
   Синий
  </color>
  <material>
   Полиэстер
  </material>
  <price>
   867439
  </price>
  <rating>
   1.62
  </rating>
  <reviews>
   543569
  </reviews>
  <new>
   -
  </new>
  <sporty>
   yes
  </sporty>
 </clothing>
 <clothing>
  <id>
   724489650
  </id>
  <name>
   Asics Sweater X-8038
  </name>
  <category>
   Sweater
  </category>
  <size>
   L
  </size>
  <color>
   Фиолетовый
  </color>
  <material>
   Хлопок
  </material>
  <price>
   651276
  </price>
  <rating>
   2.44
  </rating>
  <reviews>
   963205
  </reviews>
  <new>
   -
  </new>
  <exclusive>
   no
  </exclusive>
  <sporty>
   no
  </sporty>
 </clothing>
 <clothing>
  <id>
   549602315
  </id>
  <name>
   Fila Sweater W-5550
  </name>
  <category>
   Sweater
  </category>
  <size>
   XL
  </size>
  <color>
   Оранжевый
  </color>
  <material>
   Кожа
  </material>
  <price>
   235129
  </price>
  <rating>
   4.99
  </rating>
  <reviews>
   230560
  </reviews>
  <new>
   +
  </new>
  <sporty>
   no
  </sporty>
 </clothing>
 <clothing>
  <id>
   959594982
  </id>
  <name>
   New Balance Pants S-4410
  </name>
  <category>
   Pants
  </category>
  <size>
   M
  </size>
  <color>
   Голубой
  </color>
  <material>
   Полиэстер
  </material>
  <price>
   934243
  </price>
  <rating>
   4.58
  </rating>
  <reviews>
   862841
  </reviews>
  <new>
   -
  </new>
  <sporty>
   no
  </sporty>
 </clothing>
 <clothing>
  <id>
   538472691
  </id>
  <name>
   Adidas Blouse H-7977
  </name>
  <category>
   Blouse
  </category>
  <size>
   M
  </size>
  <color>
   Красный
  </color>
  <material>
   Полиэстер
  </material>
  <price>
   715399
  </price>
  <rating>
   2.0
  </rating>
  <reviews>
   385749
  </reviews>
  <exclusive>
   no
  </exclusive>
  <sporty>
   no
  </sporty>
 </clothing>
 <clothing>
  <id>
   539052559
  </id>
  <name>
   Vans Sweater G-7900
  </name>
  <category>
   Sweater
  </category>
  <size>
   M
  </size>
  <color>
   Фиолетовый
  </color>
  <material>
   Полиэстер
  </material>
  <price>
   649282
  </price>
  <rating>
   2.89
  </rating>
  <reviews>
   260597
  </reviews>
  <new>
   -
  </new>
  <sporty>
   no
  </sporty>
 </clothing>
 <clothing>
  <id>
   728570816
  </id>
  <name>
   DC Jeans R-7872
  </name>
  <category>
   Jeans
  </category>
  <size>
   M
  </size>
  <color>
   Фиолетовый
  </color>
  <material>
   Шелк
  </material>
  <price>
   216462
  </price>
  <rating>
   1.83
  </rating>
  <reviews>
   355782
  </reviews>
  <new>
   +
  </new>
  <exclusive>
   no
  </exclusive>
 </clothing>
 <clothing>
  <id>
   275459963
  </id>
  <name>
   Brooks Shoes B-5553
  </name>
  <category>
   Shoes
  </category>
  <size>
   M
  </size>
  <color>
   Голубой
  </color>
  <material>
   Хлопок
  </material>
  <price>
   935519
  </price>
  <rating>
   2.44
  </rating>
  <reviews>
   735339
  </reviews>
  <exclusive>
   yes
  </exclusive>
 </clothing>
 <clothing>
  <id>
   186635366
  </id>
  <name>
   Reebok Umbrellas Y-1054
  </name>
  <category>
   Umbrellas
  </category>
  <size>
   L
  </size>
  <color>
   Желтый
  </color>
  <material>
   Нейлон
  </material>
  <price>
   690302
  </price>
  <rating>
   4.44
  </rating>
  <reviews>
   912244
  </reviews>
  <new>
   -
  </new>
  <exclusive>
   no
  </exclusive>
  <sporty>
   no
  </sporty>
 </clothing>
 <clothing>
  <id>
   551037636
  </id>
  <name>
   Reebok Jeans Y-2187
  </name>
  <category>
   Jeans
  </category>
  <size>
   M
  </size>
  <color>
   Синий
  </color>
  <material>
   Вискоза
  </material>
  <price>
   361551
  </price>
  <rating>
   1.99
  </rating>
  <reviews>
   486965
  </reviews>
  <new>
   +
  </new>
  <exclusive>
   yes
  </exclusive>
 </clothing>
 <clothing>
  <id>
   269493752
  </id>
  <name>
   New Balance Shirt Q-5366
  </name>
  <category>
   Shirt
  </category>
  <size>
   M
  </size>
  <color>
   Красный
  </color>
  <material>
   Вискоза
  </material>
  <price>
   682484
  </price>
  <rating>
   1.11
  </rating>
  <reviews>
   512646
  </reviews>
  <new>
   -
  </new>
  <sporty>
   no
  </sporty>
 </clothing>
 <clothing>
  <id>
   530920792
  </id>
  <name>
   Vans Jeans B-9951
  </name>
  <category>
   Jeans
  </category>
  <size>
   S
  </size>
  <color>
   Голубой
  </color>
  <material>
   Полиэстер
  </material>
  <price>
   882237
  </price>
  <rating>
   1.82
  </rating>
  <reviews>
   559683
  </reviews>
  <new>
   +
  </new>
 </clothing>
 <clothing>
  <id>
   651343175
  </id>
  <name>
   Lacoste Dress T-9908
  </name>
  <category>
   Dress
  </category>
  <size>
   XXL
  </size>
  <color>
   Оранжевый
  </color>
  <material>
   Шерсть
  </material>
  <price>
   863502
  </price>
  <rating>
   4.4
  </rating>
  <reviews>
   597268
  </reviews>
  <new>
   -
  </new>
 </clothing>
 <clothing>
  <id>
   946760573
  </id>
  <name>
   New Balance Dress Y-4839
  </name>
  <category>
   Dress
  </category>
  <size>
   L
  </size>
  <color>
   Голубой
  </color>
  <material>
   Полиэстер
  </material>
  <price>
   539107
  </price>
  <rating>
   3.66
  </rating>
  <reviews>
   600394
  </reviews>
 </clothing>
 <clothing>
  <id>
   475704741
  </id>
  <name>
   Adidas Skirt H-5488
  </name>
  <category>
   Skirt
  </category>
  <size>
   S
  </size>
  <color>
   Синий
  </color>
  <material>
   Шелк
  </material>
  <price>
   876379
  </price>
  <rating>
   3.1
  </rating>
  <reviews>
   928014
  </reviews>
 </clothing>
 <clothing>
  <id>
   777122098
  </id>
  <name>
   Reebok Umbrellas U-2154
  </name>
  <category>
   Umbrellas
  </category>
  <size>
   L
  </size>
  <color>
   Желтый
  </color>
  <material>
   Полиэстер
  </material>
  <price>
   157606
  </price>
  <rating>
   3.47
  </rating>
  <reviews>
   972577
  </reviews>
  <new>
   -
  </new>
 </clothing>
 <clothing>
  <id>
   812165606
  </id>
  <name>
   Converse Handbags C-6455
  </name>
  <category>
   Handbags
  </category>
  <size>
   XL
  </size>
  <color>
   Фиолетовый
  </color>
  <material>
   Полиэстер
  </material>
  <price>
   884590
  </price>
  <rating>
   1.86
  </rating>
  <reviews>
   656865
  </reviews>
  <exclusive>
   no
  </exclusive>
  <sporty>
   yes
  </sporty>
 </clothing>
 <clothing>
  <id>
   711271602
  </id>
  <name>
   Brooks Dress Q-5642
  </name>
  <category>
   Dress
  </category>
  <size>
   XL
  </size>
  <color>
   Фиолетовый
  </color>
  <material>
   Вискоза
  </material>
  <price>
   876055
  </price>
  <rating>
   2.15
  </rating>
  <reviews>
   218456
  </reviews>
  <new>
   -
  </new>
  <exclusive>
   no
  </exclusive>
  <sporty>
   no
  </sporty>
 </clothing>
 <clothing>
  <id>
   358647265
  </id>
  <name>
   Lacoste Handbags J-8843
  </name>
  <category>
   Handbags
  </category>
  <size>
   S
  </size>
  <color>
   Зеленый
  </color>
  <material>
   Шелк
  </material>
  <price>
   771412
  </price>
  <rating>
   4.36
  </rating>
  <reviews>
   291579
  </reviews>
  <new>
   -
  </new>
  <exclusive>
   no
  </exclusive>
 </clothing>
 <clothing>
  <id>
   281765732
  </id>
  <name>
   Addidas Handbags S-5364
  </name>
  <category>
   Handbags
  </category>
  <size>
   S
  </size>
  <color>
   Зеленый
  </color>
  <material>
   Шерсть
  </material>
  <price>
   492446
  </price>
  <rating>
   3.92
  </rating>
  <reviews>
   243778
  </reviews>
  <exclusive>
   yes
  </exclusive>
  <sporty>
   no
  </sporty>
 </clothing>
 <clothing>
  <id>
   227642273
  </id>
  <name>
   New Balance Hat O-6311
  </name>
  <category>
   Hat
  </category>
  <size>
   L
  </size>
  <color>
   Фиолетовый
  </color>
  <material>
   Шерсть
  </material>
  <price>
   686679
  </price>
  <rating>
   1.51
  </rating>
  <reviews>
   441214
  </reviews>
  <exclusive>
   no
  </exclusive>
  <sporty>
   no
  </sporty>
 </clothing>
 <clothing>
  <id>
   445017809
  </id>
  <name>
   Ellesse Sweater G-6883
  </name>
  <category>
   Sweater
  </category>
  <size>
   XL
  </size>
  <color>
   Зеленый
  </color>
  <material>
   Лен
  </material>
  <price>
   502303
  </price>
  <rating>
   3.55
  </rating>
  <reviews>
   769505
  </reviews>
  <exclusive>
   no
  </exclusive>
  <sporty>
   no
  </sporty>
 </clothing>
 <clothing>
  <id>
   675196195
  </id>
  <name>
   Nike Sweater P-2782
  </name>
  <category>
   Sweater
  </category>
  <size>
   M
  </size>
  <color>
   Синий
  </color>
  <material>
   Шерсть
  </material>
  <price>
   304390
  </price>
  <rating>
   4.31
  </rating>
  <reviews>
   744953
  </reviews>
  <new>
   -
  </new>
 </clothing>
 <clothing>
  <id>
   205661279
  </id>
  <name>
   Brooks Umbrellas P-5365
  </name>
  <category>
   Umbrellas
  </category>
  <size>
   S
  </size>
  <color>
   Зеленый
  </color>
  <material>
   Вискоза
  </material>
  <price>
   590532
  </price>
  <rating>
   1.93
  </rating>
  <reviews>
   800537
  </reviews>
  <exclusive>
   no
  </exclusive>
  <sporty>
   yes
  </sporty>
 </clothing>
 <clothing>
  <id>
   172526800
  </id>
  <name>
   New Balance Belts M-8704
  </name>
  <category>
   Belts
  </category>
  <size>
   M
  </size>
  <color>
   Голубой
  </color>
  <material>
   Нейлон
  </material>
  <price>
   272141
  </price>
  <rating>
   4.37
  </rating>
  <reviews>
   833325
  </reviews>
  <new>
   +
  </new>
  <exclusive>
   yes
  </exclusive>
  <sporty>
   yes
  </sporty>
 </clothing>
 <clothing>
  <id>
   102915186
  </id>
  <name>
   Addidas Blouse Y-4965
  </name>
  <category>
   Blouse
  </category>
  <size>
   XL
  </size>
  <color>
   Фиолетовый
  </color>
  <material>
   Нейлон
  </material>
  <price>
   551738
  </price>
  <rating>
   2.77
  </rating>
  <reviews>
   316498
  </reviews>
  <exclusive>
   yes
  </exclusive>
 </clothing>
 <clothing>
  <id>
   287299280
  </id>
  <name>
   Puma Shirt U-4325
  </name>
  <category>
   Shirt
  </category>
  <size>
   M
  </size>
  <color>
   Синий
  </color>
  <material>
   Полиэстер
  </material>
  <price>
   361720
  </price>
  <rating>
   3.99
  </rating>
  <reviews>
   383560
  </reviews>
  <new>
   -
  </new>
  <sporty>
   no
  </sporty>
 </clothing>
 <clothing>
  <id>
   948904417
  </id>
  <name>
   PleinSport Pants M-7855
  </name>
  <category>
   Pants
  </category>
  <size>
   M
  </size>
  <color>
   Оранжевый
  </color>
  <material>
   Шелк
  </material>
  <price>
   861083
  </price>
  <rating>
   1.38
  </rating>
  <reviews>
   940177
  </reviews>
  <new>
   -
  </new>
 </clothing>
 <clothing>
  <id>
   785362119
  </id>
  <name>
   Adidas Hat G-7371
  </name>
  <category>
   Hat
  </category>
  <size>
   XXL
  </size>
  <color>
   Оранжевый
  </color>
  <material>
   Лен
  </material>
  <price>
   276992
  </price>
  <rating>
   3.56
  </rating>
  <reviews>
   536703
  </reviews>
  <sporty>
   no
  </sporty>
 </clothing>
 <clothing>
  <id>
   982197451
  </id>
  <name>
   Converse Pants F-9382
  </name>
  <category>
   Pants
  </category>
  <size>
   M
  </size>
  <color>
   Оранжевый
  </color>
  <material>
   Шелк
  </material>
  <price>
   998953
  </price>
  <rating>
   2.64
  </rating>
  <reviews>
   860352
  </reviews>
  <exclusive>
   yes
  </exclusive>
  <sporty>
   yes
  </sporty>
 </clothing>
 <clothing>
  <id>
   561661144
  </id>
  <name>
   Ellesse Handbags I-6971
  </name>
  <category>
   Handbags
  </category>
  <size>
   M
  </size>
  <color>
   Оранжевый
  </color>
  <material>
   Нейлон
  </material>
  <price>
   690019
  </price>
  <rating>
   2.03
  </rating>
  <reviews>
   134319
  </reviews>
  <new>
   +
  </new>
  <exclusive>
   yes
  </exclusive>
  <sporty>
   no
  </sporty>
 </clothing>
 <clothing>
  <id>
   525352491
  </id>
  <name>
   Ellesse Jeans E-9463
  </name>
  <category>
   Jeans
  </category>
  <size>
   S
  </size>
  <color>
   Зеленый
  </color>
  <material>
   Полиэстер
  </material>
  <price>
   953449
  </price>
  <rating>
   1.66
  </rating>
  <reviews>
   131674
  </reviews>
  <new>
   -
  </new>
  <exclusive>
   yes
  </exclusive>
  <sporty>
   no
  </sporty>
 </clothing>
 <clothing>
  <id>
   250690320
  </id>
  <name>
   Fila T-shirt R-9937
  </name>
  <category>
   T-shirt
  </category>
  <size>
   XL
  </size>
  <color>
   Синий
  </color>
  <material>
   Хлопок
  </material>
  <price>
   714632
  </price>
  <rating>
   4.46
  </rating>
  <reviews>
   65469
  </reviews>
  <new>
   +
  </new>
  <sporty>
   no
  </sporty>
 </clothing>
 <clothing>
  <id>
   754421935
  </id>
  <name>
   Addidas Belts S-2977
  </name>
  <category>
   Belts
  </category>
  <size>
   XXL
  </size>
  <color>
   Оранжевый
  </color>
  <material>
   Полиэстер
  </material>
  <price>
   642852
  </price>
  <rating>
   2.06
  </rating>
  <reviews>
   570319
  </reviews>
  <new>
   -
  </new>
  <sporty>
   yes
  </sporty>
 </clothing>
 <clothing>
  <id>
   851612571
  </id>
  <name>
   Brooks Dress R-1330
  </name>
  <category>
   Dress
  </category>
  <size>
   S
  </size>
  <color>
   Фиолетовый
  </color>
  <material>
   Вискоза
  </material>
  <price>
   168764
  </price>
  <rating>
   4.49
  </rating>
  <reviews>
   80437
  </reviews>
  <sporty>
   no
  </sporty>
 </clothing>
 <clothing>
  <id>
   640063556
  </id>
  <name>
   Converse Hat U-3085
  </name>
  <category>
   Hat
  </category>
  <size>
   M
  </size>
  <color>
   Синий
  </color>
  <material>
   Шелк
  </material>
  <price>
   330813
  </price>
  <rating>
   3.03
  </rating>
  <reviews>
   708288
  </reviews>
  <new>
   -
  </new>
  <sporty>
   no
  </sporty>
 </clothing>
 <clothing>
  <id>
   247160526
  </id>
  <name>
   Vans Gloves H-9697
  </name>
  <category>
   Gloves
  </category>
  <size>
   S
  </size>
  <color>
   Красный
  </color>
  <material>
   Шерсть
  </material>
  <price>
   278152
  </price>
  <rating>
   3.06
  </rating>
  <reviews>
   998863
  </reviews>
  <exclusive>
   no
  </exclusive>
  <sporty>
   no
  </sporty>
 </clothing>
 <clothing>
  <id>
   969643156
  </id>
  <name>
   Reebok Belts A-9910
  </name>
  <category>
   Belts
  </category>
  <size>
   M
  </size>
  <color>
   Желтый
  </color>
  <material>
   Лен
  </material>
  <price>
   832258
  </price>
  <rating>
   4.47
  </rating>
  <reviews>
   906076
  </reviews>
  <new>
   +
  </new>
  <exclusive>
   no
  </exclusive>
  <sporty>
   no
  </sporty>
 </clothing>
 <clothing>
  <id>
   961318848
  </id>
  <name>
   PleinSport Blouse T-4421
  </name>
  <category>
   Blouse
  </category>
  <size>
   L
  </size>
  <color>
   Красный
  </color>
  <material>
   Нейлон
  </material>
  <price>
   376012
  </price>
  <rating>
   2.86
  </rating>
  <reviews>
   749330
  </reviews>
  <new>
   +
  </new>
  <exclusive>
   no
  </exclusive>
 </clothing>
 <clothing>
  <id>
   785389018
  </id>
  <name>
   Puma Belts K-1176
  </name>
  <category>
   Belts
  </category>
  <size>
   L
  </size>
  <color>
   Голубой
  </color>
  <material>
   Шерсть
  </material>
  <price>
   194137
  </price>
  <rating>
   1.34
  </rating>
  <reviews>
   889340
  </reviews>
  <sporty>
   no
  </sporty>
 </clothing>
</clothing-items>
